README.rst
setup.cfg
setup.py
Apiwatcher_Pyclient.egg-info/PKG-INFO
Apiwatcher_Pyclient.egg-info/SOURCES.txt
Apiwatcher_Pyclient.egg-info/dependency_links.txt
Apiwatcher_Pyclient.egg-info/requires.txt
Apiwatcher_Pyclient.egg-info/top_level.txt
apiwatcher_pyclient/__init__.py
apiwatcher_pyclient/client.py
apiwatcher_pyclient/exceptions.py