Metadata-Version: 1.1
Name: Apiwatcher-Pyclient
Version: 0.1.2
Summary: A simple client for Apiwatcher platform
Home-page: https://github.com/apiwatcher/apiwatcher-pyclient
Author: Karel Jakubec
Author-email: karel@jakubec.name
License: MIT
Keywords: http client apiwatcher
Platform: UNKNOWN
Classifier: Development Status :: 3 - Alpha
Classifier: Intended Audience :: Developers
Classifier: Topic :: Software Development :: Libraries :: Python Modules
Classifier: Topic :: Software Development :: Libraries
Classifier: License :: OSI Approved :: MIT License
Classifier: Programming Language :: Python :: 2
Classifier: Programming Language :: Python :: 2.7
